RISCV-SINGLE-CYCLE/Components/alu.v
module alu(
    input wire [31:0] operandA,
    input wire [31:0] operandB,
    input wire [3:0] aluControl,
    output reg [31:0] result
);
    always@(*)
        begin
            case(aluControl)
                4'b0000 : result = operandA + operandB; // ADD
                4'b0001 : result = operandA - operandB; // SUB
                4'b0010 : result = operandA & operandB; // AND
                4'b0011 : result = operandA | operandB; // OR
                4'b0100 : result = operandA ^ operandB; // XOR
                4'b0101 : result = operandA << 1; // SLL
                4'b0110 : result = operandA >> 1; // SRL
                4'b0111 : result = $signed(operandA) >>> 1; // SRA
                4'b1000 : result = $signed(operandA) < $signed(operandB) ? 1 : 0; // SLTU
                4'b1001 : result = operandA < operandB ? 1 : 0; // SLT
                default : result = 0;
            endcase
        end
endmodule

RISCV-SINGLE-CYCLE/Testbench/alu_tb.v
module alu_tb;
    reg [31:0] operandA, operandB;
    reg [3:0] aluControl;
    wire [31:0] result;
    alu alu0(
        .operandA(operandA),
        .operandB(operandB),
        .aluControl(aluControl),
        .result(result)
    );
    initial
        begin
            $dumpfile("Dumpfiles/alu_tb.vcd");
            $dumpvars(0, alu_tb);
            aluControl = 4'b0000; // ADD
            operandA = 32'h00000001;
            operandB = 32'h00000001;
            #10;
            aluControl = 4'b0001; // SUB
            operandA = 32'h00000002;
            operandB = 32'h00000001;
            #10;
            aluControl = 4'b0010; // AND
            operandA = 32'h00000001;
            operandB = 32'h00000001;
            #10;
            aluControl = 4'b0011; // OR
            operandA = 32'h00000001;
            operandB = 32'h00000001;
            #10;
            aluControl = 4'b0100; // XOR
            operandA = 32'h00000001;
            operandB = 32'h00000001;
            #10;
            aluControl = 4'b0101; // SLL
            operandA = 32'h00000001;
            operandB = 32'h00000001;
            #10;
            aluControl = 4'b0110; // SRL
            operandA = 32'h00000001;
            operandB = 32'h00000001;
            #10;
            aluControl = 4'b0111; // SRA
            operandA = 32'h80000000;
            operandB = 32'h00000001;
            #10;
            aluControl = 4'b1000; // SLT
            operandA = 32'h00000001;
            operandB = 32'h00000001;
            #10;
            aluControl = 4'b1001; // SLTU
            operandA = 32'h00000001;
            operandB = 32'h00000001;
            #10;
            $finish;
        end
endmodule

RISCV-SINGLE-CYCLE/Dumpfiles/alu_tb.vcd
$date
	Mon Feb 17 14:49:31 2025
$end
$version
	Icarus Verilog
$end
$timescale
	1s
$end
$scope module alu_tb $end
$var wire 32 ! result [31:0] $end
$var reg 4 " aluControl [3:0] $end
$var reg 32 # operandA [31:0] $end
$var reg 32 $ operandB [31:0] $end
$scope module alu0 $end
$var wire 4 % aluControl [3:0] $end
$var wire 32 & operandA [31:0] $end
$var wire 32 ' operandB [31:0] $end
$var reg 32 ( result [31:0] $end
$upscope $end
$upscope $end
$enddefinitions $end
$comment Show the parameter values. $end
$dumpall
$end
#0
$dumpvars
b10 (
b1 '
b1 &
b0 %
b1 $
b1 #
b0 "
b10 !
$end
#10
b1 !
b1 (
b10 #
b10 &
b1 "
b1 %
#20
b1 #
b1 &
b10 "
b10 %
#30
b11 "
b11 %
#40
b0 !
b0 (
b100 "
b100 %
#50
b10 !
b10 (
b101 "
b101 %
#60
b0 !
b0 (
b110 "
b110 %
#70
b11000000000000000000000000000000 !
b11000000000000000000000000000000 (
b10000000000000000000000000000000 #
b10000000000000000000000000000000 &
b111 "
b111 %
#80
b0 !
b0 (
b1 #
b1 &
b1000 "
b1000 %
#90
b1001 "
b1001 %
