RISCV-SINGLE-CYCLE/Components/data_memory.v
module data_memory(
    input wire clk,
    input wire reset,
    input wire [31:0] address,
    input wire [7:0] write_data,
    input wire write_enable,
    input wire read_enable,
    output reg [7:0] read_data
);

    reg [7:0] memory [0:511];
    integer i;

    always @(posedge clk) begin // Write operation
        if (reset == 1'b1) begin
            for (i = 0; i < 512; i = i + 1) begin
                memory[i] <= 8'b0;
            end
        end else if (write_enable == 1'b1) begin
            memory[address] <= write_data;
        end
    end

   always@(address,read_enable) // Read operation
            begin
                if(read_enable == 1'b1)
                    begin
                    read_data <= memory[address];
                    end
                else 
                    begin
                    read_data <= 8'bz;
                    end    
            end 
endmodule

RISCV-SINGLE-CYCLE/Testbench/data_memory_tb.v
module data_memory_tb;
    reg clk;
    reg reset;
    reg [31:0] address;
    reg [7:0] write_data;
    reg write_enable;
    reg read_enable;
    wire [7:0] read_data;
    
    data_memory data_memory0 (
        .clk(clk),
        .reset(reset),
        .address(address),
        .write_data(write_data),
        .write_enable(write_enable),
        .read_enable(read_enable),
        .read_data(read_data)
    );
    initial begin
        $dumpfile("Dumpfiles/data_memory.vcd");
        $dumpvars(0, data_memory_tb);
        clk = 1'b0;
        address = 8'b0;
        write_data = 8'b0;
        write_enable = 1'b0;
        read_enable = 1'b0;
        reset = 1'b0;
        #4 reset = 1'b1;
        #8 reset = 1'b0;
        #10 write_enable = 1'b1;
        #10 address = 32'h00000004;
        #10 write_data = 8'hFF;
        #10 write_enable = 1'b0;
        #10 read_enable = 1'b1;
        #10 address = 32'h00000004;
        #10 read_enable = 1'b0;
        #10 $finish;
    end
    always
        #5 clk = ~clk;
endmodule

RISCV-SINGLE-CYCLE/Dumpfiles/data_memory.vcd
$date
	Tue Feb 18 18:15:40 2025
$end
$version
	Icarus Verilog
$end
$timescale
	1s
$end
$scope module data_memory_tb $end
$var wire 8 ! read_data [7:0] $end
$var reg 32 " address [31:0] $end
$var reg 1 # clk $end
$var reg 1 $ read_enable $end
$var reg 1 % reset $end
$var reg 8 & write_data [7:0] $end
$var reg 1 ' write_enable $end
$scope module data_memory0 $end
$var wire 32 ( address [31:0] $end
$var wire 1 # clk $end
$var wire 1 $ read_enable $end
$var wire 1 % reset $end
$var wire 8 ) write_data [7:0] $end
$var wire 1 ' write_enable $end
$var reg 8 * read_data [7:0] $end
$var integer 32 + i [31:0] $end
$upscope $end
$upscope $end
$enddefinitions $end
$comment Show the parameter values. $end
$dumpall
$end
#0
$dumpvars
bx +
bz *
b0 )
b0 (
0'
b0 &
0%
0$
0#
b0 "
bz !
$end
#4
b1000000000000 +
1%
#5
b1000000000000 +
1#
#10
0#
#12
0%
#15
1#
#20
0#
#22
1'
#25
1#
#30
0#
#32
b100 "
b100 (
#35
1#
#40
0#
#42
b11111111 &
b11111111 )
#45
1#
#50
0#
#52
0'
#55
1#
#60
0#
#62
b11111111 !
b11111111 *
1$
#65
1#
#70
0#
#75
1#
#80
0#
#82
bz !
bz *
0$
