RISCV-SINGLE-CYCLE/Components/instruction_memory.v
module instruction_memory(
    input wire reset,
    input wire chip_select,
    input wire [31:0] address,
    output reg [31:0] instruction
);
    
        reg [31:0] mem[0:1023];
        integer i;
        initial 
            begin
                $readmemh("E:/Verilog/IOP/instruction.mif",mem);
            end
        always@(posedge reset and chip_select == 1'b1)
            begin
                if(reset == 1'b1)
                    begin
                        for(i=0;i<1024;i=i+1)
                            mem[i] <= 32'b0;
                    end
            end
        always@(chip_select,address)
            begin
                if(chip_select == 1'b1)
                    begin
                        instruction <= mem[address[31:2]]; // Word Addressable Memory as Instruction are of word size
                    end
                else 
                    instruction <= 32'bz;    
            end    
endmodule

RISCV-SINGLE-CYCLE/Testbench/instruction_memory_tb.v
module instruction_memory_tb;
    reg reset;
    reg chip_select;
    reg [31:0] address;
    wire [31:0] instruction;
    instruction_memory instruction_memory_0(
        .reset(reset),
        .chip_select(chip_select),
        .address(address),
        .instruction(instruction)
    );
    initial
        begin
            $dumpfile("Dumpfiles/instruction_memory.vcd");
            $dumpvars(0, instruction_memory_tb);
            reset = 1'b0;
            address = 1'b0;
            chip_select = 1'b1;
            #10 address = 32'h00000000;
            #10 address = 32'h00000004;
            #10 address = 32'h00000008;
            #10 address = 32'h0000000C;
            #10 address = 32'h00000010;
            #10 address = 32'h00000014;
            #10 address = 32'h00000018;
            #10 address = 32'h0000001C;
            #10 address = 32'h00000020;
            #10 chip_select = 1'b0;
            #10 $finish;
        end
endmodule

RISCV-SINGLE-CYCLE/Dumpfiles/instruction_memory.vcd
$date
	Tue Feb 18 17:18:42 2025
$end
$version
	Icarus Verilog
$end
$timescale
	1s
$end
$scope module instruction_memory_tb $end
$var wire 32 ! instruction [31:0] $end
$var reg 32 " address [31:0] $end
$var reg 1 # chip_select $end
$var reg 1 $ reset $end
$scope module instruction_memory_0 $end
$var wire 32 % address [31:0] $end
$var wire 1 # chip_select $end
$var wire 1 $ reset $end
$var reg 32 & instruction [31:0] $end
$var integer 32 ' i [31:0] $end
$upscope $end
$upscope $end
$enddefinitions $end
$comment Show the parameter values. $end
$dumpall
$end
#0
$dumpvars
bx '
b10010011 &
b0 %
0$
1#
b0 "
b10010011 !
$end
#20
b100110011 !
b100110011 &
b100 "
b100 %
#30
b10011 !
b10011 &
b1000 "
b1000 %
#40
b1100011 !
b1100011 &
b1100 "
b1100 %
#50
b110010011 !
b110010011 &
b10000 "
b10000 %
#60
b10010011 !
b10010011 &
b10100 "
b10100 %
#70
b100110011 !
b100110011 &
b11000 "
b11000 %
#80
b1100010011 !
b1100010011 &
b11100 "
b11100 %
#90
bx !
bx &
b100000 "
b100000 %
#100
bz !
bz &
0#
