RISCV-SINGLE-CYCLE/Components/register_file.v
module register_file(
    input wire clk,
    input wire reset,
    input wire read_enable,
    input wire [4:0] read_addr1,
    input wire [4:0] read_addr2,
    input wire write_enable,
    input wire [4:0] write_addr,
    input wire [31:0] write_data,
    output reg [31:0] data_out1,
    output reg [31:0] data_out2,
    output wire [31:0] a
);
    reg [31:0] data [0:31];
    assign a = data[31];
    integer i;
    always@(posedge clk or posedge reset) begin
        if(reset == 1'b1) begin
            for (i = 0; i < 32; i = i + 1) begin
                data[i] <= 32'b0;
            end
        end else begin
                if(write_enable == 1'b1) begin
                    data[write_addr] <= write_data;
                end
        end
    end
    always@(*) begin
        if(read_enable == 1'b1) begin
            data_out1 = data[read_addr1];
            data_out2 = data[read_addr2];
        end 
        else 
            begin
            data_out1 = 32'bz;
            data_out2 = 32'bz;
            end
    end 
endmodule

RISCV-SINGLE-CYCLE/Testbench/register_file_tb.v
module register_file_tb;
    reg clk;
    reg reset;
    reg read_enable;
    reg [4:0] read_addr1;
    reg [4:0] read_addr2;
    reg [4:0] write_addr;
    reg write_enable;
    reg [31:0] write_data;
    wire [31:0] data_out1;
    wire [31:0] data_out2;
    wire [31:0] a;
    integer i;
    register_file rf(
        .clk(clk),
        .reset(reset),
        .read_enable(read_enable),
        .write_enable(write_enable),
        .read_addr1(read_addr1),
        .read_addr2(read_addr2),
        .write_addr(write_addr),
        .write_data(write_data),
        .data_out1(data_out1),
        .data_out2(data_out2),
        .a(a)
    );
    initial
        forever #5 clk = ~clk;

    initial begin
        $dumpfile("Dumpfiles/register_file.vcd");
        $dumpvars(0, register_file_tb);
         write_enable = 1'b0;
         write_data = 32'b0;
         write_addr = 5'b00000;
        read_enable = 1'b0;
        read_addr1 = 5'b00000;
        read_addr2 = 5'b00000;
        clk = 1'b0;
        reset = 1'b0;
        #10 reset = 1'b1;
        #10 reset = 1'b0;
        write_enable = 1'b1;
        for(i = 0; i < 32; i = i+1) begin
            write_addr = i;
            write_data = i;
            #10;
        end
        write_enable = 1'b0;
        read_enable = 1'b1;
        read_addr1 = 5'b00000;
        read_addr2 = 5'b00001;
        #10 read_addr2 = 5'b11110;
        #10 $finish;
    end
endmodule

RISCV-SINGLE-CYCLE/Dumpfiles/register_file.vcd
$date
	Wed Feb 19 04:01:59 2025
$end
$version
	Icarus Verilog
$end
$timescale
	1s
$end
$scope module register_file_tb $end
$var wire 32 ! data_out2 [31:0] $end
$var wire 32 " data_out1 [31:0] $end
$var wire 32 # a [31:0] $end
$var reg 1 $ clk $end
$var reg 5 % read_addr1 [4:0] $end
$var reg 5 & read_addr2 [4:0] $end
$var reg 1 ' read_enable $end
$var reg 1 ( reset $end
$var reg 5 ) write_addr [4:0] $end
$var reg 32 * write_data [31:0] $end
$var reg 1 + write_enable $end
$var integer 32 , i [31:0] $end
$scope module rf $end
$var wire 32 - a [31:0] $end
$var wire 1 $ clk $end
$var wire 5 . read_addr1 [4:0] $end
$var wire 5 / read_addr2 [4:0] $end
$var wire 1 ' read_enable $end
$var wire 1 ( reset $end
$var wire 5 0 write_addr [4:0] $end
$var wire 32 1 write_data [31:0] $end
$var wire 1 + write_enable $end
$var reg 32 2 data_out1 [31:0] $end
$var reg 32 3 data_out2 [31:0] $end
$var integer 32 4 i [31:0] $end
$upscope $end
$upscope $end
$enddefinitions $end
$comment Show the parameter values. $end
$dumpall
$end
#0
$dumpvars
bx 4
bz 3
bz 2
b0 1
b0 0
b0 /
b0 .
bx -
bx ,
0+
b0 *
b0 )
0(
0'
b0 &
b0 %
0$
bx #
bz "
bz !
$end
#5
1$
#10
b0 #
b0 -
b100000 4
0$
1(
#15
b100000 4
1$
#20
0$
b0 ,
1+
0(
#25
1$
#30
0$
b1 ,
#35
1$
#40
0$
b10 ,
b1 *
b1 1
b1 )
b1 0
#45
1$
#50
0$
b11 ,
b10 *
b10 1
b10 )
b10 0
#55
1$
#60
0$
b100 ,
b11 *
b11 1
b11 )
b11 0
#65
1$
#70
0$
b101 ,
b100 *
b100 1
b100 )
b100 0
#75
1$
#80
0$
b110 ,
b101 *
b101 1
b101 )
b101 0
#85
1$
#90
0$
b111 ,
b110 *
b110 1
b110 )
b110 0
#95
1$
#100
0$
b1000 ,
b111 *
b111 1
b111 )
b111 0
#105
1$
#110
0$
b1001 ,
b1000 *
b1000 1
b1000 )
b1000 0
#115
1$
#120
0$
b1010 ,
b1001 *
b1001 1
b1001 )
b1001 0
#125
1$
#130
0$
b1011 ,
b1010 *
b1010 1
b1010 )
b1010 0
#135
1$
#140
0$
b1100 ,
b1011 *
b1011 1
b1011 )
b1011 0
#145
1$
#150
0$
b1101 ,
b1100 *
b1100 1
b1100 )
b1100 0
#155
1$
#160
0$
b1110 ,
b1101 *
b1101 1
b1101 )
b1101 0
#165
1$
#170
0$
b1111 ,
b1110 *
b1110 1
b1110 )
b1110 0
#175
1$
#180
0$
b10000 ,
b1111 *
b1111 1
b1111 )
b1111 0
#185
1$
#190
0$
b10001 ,
b10000 *
b10000 1
b10000 )
b10000 0
#195
1$
#200
0$
b10010 ,
b10001 *
b10001 1
b10001 )
b10001 0
#205
1$
#210
0$
b10011 ,
b10010 *
b10010 1
b10010 )
b10010 0
#215
1$
#220
0$
b10100 ,
b10011 *
b10011 1
b10011 )
b10011 0
#225
1$
#230
0$
b10101 ,
b10100 *
b10100 1
b10100 )
b10100 0
#235
1$
#240
0$
b10110 ,
b10101 *
b10101 1
b10101 )
b10101 0
#245
1$
#250
0$
b10111 ,
b10110 *
b10110 1
b10110 )
b10110 0
#255
1$
#260
0$
b11000 ,
b10111 *
b10111 1
b10111 )
b10111 0
#265
1$
#270
0$
b11001 ,
b11000 *
b11000 1
b11000 )
b11000 0
#275
1$
#280
0$
b11010 ,
b11001 *
b11001 1
b11001 )
b11001 0
#285
1$
#290
0$
b11011 ,
b11010 *
b11010 1
b11010 )
b11010 0
#295
1$
#300
0$
b11100 ,
b11011 *
b11011 1
b11011 )
b11011 0
#305
1$
#310
0$
b11101 ,
b11100 *
b11100 1
b11100 )
b11100 0
#315
1$
#320
0$
b11110 ,
b11101 *
b11101 1
b11101 )
b11101 0
#325
1$
#330
0$
b11111 ,
b11110 *
b11110 1
b11110 )
b11110 0
#335
1$
#340
b1 !
b1 3
b0 "
b0 2
0$
b1 &
b1 /
1'
0+
b100000 ,
b11111 *
b11111 1
b11111 )
b11111 0
#345
1$
#350
b11110 !
b11110 3
0$
b11110 &
b11110 /
